onebot_qqguild_extension/__init__.py
onebot_qqguild_extension/bot.py
onebot_qqguild_extension/event.py
onebot_qqguild_extension-0.1.1.dist-info/LICENSE
onebot_qqguild_extension-0.1.1.dist-info/METADATA
onebot_qqguild_extension-0.1.1.dist-info/WHEEL
onebot_qqguild_extension-0.1.1.dist-info/RECORD
