Metadata-Version: 2.1
Name: onebot-qqguild-extension
Version: 0.1.1
Summary: 
License: MIT
Author: hemengyang
Author-email: hmy0119@gmail.com
Requires-Python: >=3.8,<4.0
Classifier: License :: OSI Approved :: MIT License
Classifier: Programming Language :: Python :: 3
Classifier: Programming Language :: Python :: 3.8
Classifier: Programming Language :: Python :: 3.9
Classifier: Programming Language :: Python :: 3.10
Classifier: Programming Language :: Python :: 3.11
Requires-Dist: nonebot-adapter-onebot (>=2.2.3,<3.0.0)
Requires-Dist: nonebot2 (>=2.0.0-rc.1,<3.0.0)
